GenEpub/__init__.py
GenEpub/util.py
GenEpub/assets/Style.css
GenEpub/assets/__init__.py
GenEpub/assets/article.j2
GenEpub/assets/container.xml
GenEpub/assets/content.j2
GenEpub/assets/mimetype
GenEpub/assets/toc.j2
GenEpub-2023.7.9.0.dist-info/LICENSE
GenEpub-2023.7.9.0.dist-info/METADATA
GenEpub-2023.7.9.0.dist-info/WHEEL
GenEpub-2023.7.9.0.dist-info/top_level.txt
GenEpub-2023.7.9.0.dist-info/RECORD
