Metadata-Version: 2.1
Name: GenEpub
Version: 2023.7.9.0
Summary: GenEpub，用于生成 EPUB 的小工具
Home-page: https://github.com/apachecn/gen-epub
Author: wizardforcel
Author-email: wizard.z@qq.com
Keywords: epub,ebook,电子书
Classifier: Development Status :: 4 - Beta
Classifier: Environment :: Console
Classifier: Intended Audience :: Developers
Classifier: Intended Audience :: End Users/Desktop
Classifier: License :: Other/Proprietary License
Classifier: Natural Language :: Chinese (Simplified)
Classifier: Natural Language :: English
Classifier: Operating System :: OS Independent
Classifier: Programming Language :: Python :: 3
Classifier: Programming Language :: Python :: 3 :: Only
Classifier: Programming Language :: Python :: 3.6
Classifier: Programming Language :: Python :: 3.7
Classifier: Topic :: Text Processing :: Markup :: HTML
Classifier: Topic :: Utilities
Requires-Python: >=3.6
License-File: LICENSE
Requires-Dist: jinja2
